README.txt
setup.py
wsgintegrate/__init__.py
wsgintegrate/dispatcher.py
wsgintegrate/factory.py
wsgintegrate/main.py
wsgintegrate/match.py
wsgintegrate/server.py
wsgintegrate/web.py
wsgintegrate.egg-info/PKG-INFO
wsgintegrate.egg-info/SOURCES.txt
wsgintegrate.egg-info/dependency_links.txt
wsgintegrate.egg-info/entry_points.txt
wsgintegrate.egg-info/not-zip-safe
wsgintegrate.egg-info/requires.txt
wsgintegrate.egg-info/top_level.txt