Metadata-Version: 1.0
Name: wsgintegrate
Version: 0.1.2
Summary: WSGI integration layer
Home-page: http://k0s.org/
Author: Jeff Hammel
Author-email: k0scist@gmail.com
License: GPL
Platform: UNKNOWN
